a7585d/__init__.py
a7585d/a7585d.py
a7585d-1.0.3.dist-info/METADATA
a7585d-1.0.3.dist-info/WHEEL
a7585d-1.0.3.dist-info/RECORD
