Metadata-Version: 2.1
Name: a7585d
Version: 1.0.3
Summary: Library to control A7585D Caen HV module (all versions)
Project-URL: Homepage, https://github.com/NuclearInstruments/a7585d-python
Project-URL: Bug Tracker, https://github.com/NuclearInstruments/a7585d-python
Author-email: Andrea Abba <abba@nuclearinstruments.eu>
Keywords: A7585D,CAEN,HV,Nuclear Instruments,SiPM bias
Classifier: License :: OSI Approved :: MIT License
Classifier: Operating System :: OS Independent
Classifier: Programming Language :: Python :: 3
Requires-Python: >=3.5
Requires-Dist: pyserial
